easydata/__init__.py
easydata/easydata.py
easydata/deploy/configs/ppdataaug_clas.yaml
easydata/deploy/configs/ppdataaug_ocr_img2img.yaml
easydata/deploy/configs/ppdataaug_ocr_text2img.yaml
easydata/deploy/configs/ppdataaug_shitu.yaml
easydata/deploy/configs/ppdataclean.yaml
easydata/deploy/configs/ppcv/big_model_classification.yaml
easydata/deploy/configs/ppcv/clarity_assessment.yaml
easydata/deploy/configs/ppcv/code_exists.yaml
easydata/deploy/configs/ppcv/feature_extract.yaml
easydata/deploy/configs/ppcv/image_orientation.yaml
easydata/deploy/configs/ppcv/text_recognition.yaml
easydata/deploy/configs/ppdataaug/ocr_rec_gen.yaml
easydata/deploy/ppcv/__init__.py
easydata/deploy/ppcv/__pycache__/__init__.cpython-37.pyc
easydata/deploy/ppcv/core/__init__.py
easydata/deploy/ppcv/core/config.py
easydata/deploy/ppcv/core/framework.py
easydata/deploy/ppcv/core/workspace.py
easydata/deploy/ppcv/core/__pycache__/__init__.cpython-37.pyc
easydata/deploy/ppcv/core/__pycache__/config.cpython-37.pyc
easydata/deploy/ppcv/core/__pycache__/framework.cpython-37.pyc
easydata/deploy/ppcv/core/__pycache__/workspace.cpython-37.pyc
easydata/deploy/ppcv/engine/__init__.py
easydata/deploy/ppcv/engine/pipeline.py
easydata/deploy/ppcv/engine/__pycache__/__init__.cpython-37.pyc
easydata/deploy/ppcv/engine/__pycache__/pipeline.cpython-37.pyc
easydata/deploy/ppcv/model_zoo/__init__.py
easydata/deploy/ppcv/model_zoo/model_zoo.py
easydata/deploy/ppcv/model_zoo/__pycache__/__init__.cpython-37.pyc
easydata/deploy/ppcv/model_zoo/__pycache__/model_zoo.cpython-37.pyc
easydata/deploy/ppcv/ops/__init__.py
easydata/deploy/ppcv/ops/base.py
easydata/deploy/ppcv/ops/general_data_obj.py
easydata/deploy/ppcv/ops/predictor.py
easydata/deploy/ppcv/ops/__pycache__/__init__.cpython-37.pyc
easydata/deploy/ppcv/ops/__pycache__/base.cpython-37.pyc
easydata/deploy/ppcv/ops/__pycache__/predictor.cpython-37.pyc
easydata/deploy/ppcv/ops/connector/__init__.py
easydata/deploy/ppcv/ops/connector/base.py
easydata_python-0.5.1.dist-info/LICENSE
easydata_python-0.5.1.dist-info/METADATA
easydata_python-0.5.1.dist-info/WHEEL
easydata_python-0.5.1.dist-info/entry_points.txt
easydata_python-0.5.1.dist-info/top_level.txt
easydata_python-0.5.1.dist-info/RECORD
